custom_logger/__init__.py
custom_logger/__main__.py
custom_logger/logger.py
custom_logger/__pycache__/__main__.cpython-313.pyc
custom_logger_pkg-0.2.0.dist-info/licenses/LICENSE
custom_logger_pkg-0.2.0.dist-info/METADATA
custom_logger_pkg-0.2.0.dist-info/WHEEL
custom_logger_pkg-0.2.0.dist-info/entry_points.txt
custom_logger_pkg-0.2.0.dist-info/top_level.txt
custom_logger_pkg-0.2.0.dist-info/RECORD
