Metadata-Version: 2.4
Name: custom-logger-pkg
Version: 0.2.0
Summary: Professional Object-Oriented Logger for Python - Enhanced logging with SOLID principles
Author-email: Saman Naruee <samannaruee@gmail.com>
Maintainer-email: Saman Naruee <samannaruee@gmail.com>
License: MIT
Project-URL: Homepage, https://github.com/Saman-naruee/Custom-Logger
Project-URL: Documentation, https://custom-logger.readthedocs.io/
Project-URL: Repository, https://github.com/Saman-naruee/Custom-Logger.git
Project-URL: Issues, https://github.com/Saman-naruee/Custom-Logger/issues
Project-URL: Changelog, https://github.com/Saman-naruee/Custom-Logger/blob/main/CHANGELOG.md
Keywords: logging,logger,object-oriented,colorama,development
Classifier: Development Status :: 5 - Production/Stable
Classifier: Intended Audience :: Developers
Classifier: License :: OSI Approved :: MIT License
Classifier: Programming Language :: Python :: 3
Classifier: Programming Language :: Python :: 3.7
Classifier: Programming Language :: Python :: 3.8
Classifier: Programming Language :: Python :: 3.9
Classifier: Programming Language :: Python :: 3.10
Classifier: Programming Language :: Python :: 3.11
Classifier: Programming Language :: Python :: 3.12
Classifier: Topic :: Software Development :: Libraries :: Python Modules
Classifier: Topic :: System :: Logging
Classifier: Operating System :: OS Independent
Requires-Python: >=3.7
License-File: LICENSE
Requires-Dist: colorama>=0.4.4
Provides-Extra: dev
Requires-Dist: pytest>=6.0; extra == "dev"
Requires-Dist: black; extra == "dev"
Requires-Dist: flake8; extra == "dev"
Requires-Dist: mypy; extra == "dev"
Requires-Dist: coverage; extra == "dev"
Requires-Dist: sphinx; extra == "dev"
Requires-Dist: sphinx-rtd-theme; extra == "dev"
Dynamic: license-file
